SOURCE/uart_receiver.v
module uart_receiver(
    input wire clk,
    input wire rst,
    input wire baud_tick_16x,
    input wire rx_serial,
    output reg [7:0] rx_data,
    output reg rx_ready,
    output reg rx_error
);

    localparam IDLE = 3'b000;
    localparam START = 3'b001;
    localparam DATA = 3'b010;
    localparam STOP = 3'b011;

    reg [2:0] state;
    reg [2:0] bit_counter;
    reg [7:0] rx_shift_reg;
    reg [3:0] sample_counter;
    reg [2:0] rx_sync;
    reg prev_rx_filtered;
    reg [1:0] rx_ready_hold;

    always @(posedge clk or posedge rst) begin
        if (rst) begin
            rx_sync <= 3'b111;
            prev_rx_filtered <= 1;
            rx_ready <= 0;
            rx_ready_hold <= 0;
        end else begin
            rx_sync <= {rx_sync[1:0], rx_serial};
            prev_rx_filtered <= rx_sync[2];

            if (rx_ready_hold > 0) begin
                rx_ready_hold <= rx_ready_hold - 1;
                rx_ready <= 1;
            end else begin
                rx_ready <= 0;
            end
        end
    end

    wire rx_filtered = rx_sync[2];
    wire start_bit_detected = prev_rx_filtered & ~rx_filtered;

    always @(posedge clk or posedge rst) begin
        if (rst) begin
            state <= IDLE;
            rx_error <= 0;
            bit_counter <= 0;
            sample_counter <= 0;
            rx_shift_reg <= 0;
        end else begin
            if (rx_error) rx_error <= 0;

            case (state)
                IDLE: begin
                    if (start_bit_detected) begin
                        state <= START;
                        sample_counter <= 0;
                    end
                end
                START: if (baud_tick_16x) begin
                    sample_counter <= sample_counter + 1;
                    if (sample_counter == 7) begin
                        if (rx_filtered == 0) begin
                            state <= DATA;
                            bit_counter <= 0;
                            sample_counter <= 0;
                        end else begin
                            rx_error <= 1;
                            state <= IDLE;
                        end
                    end
                end
                DATA: if (baud_tick_16x) begin
                    sample_counter <= sample_counter + 1;
                    if (sample_counter == 15) begin
                        rx_shift_reg[bit_counter] <= rx_filtered;
                        bit_counter <= bit_counter + 1;
                        sample_counter <= 0;
                        if (bit_counter == 7) state <= STOP;
                    end
                end
                STOP: if (baud_tick_16x) begin
                    sample_counter <= sample_counter + 1;
                    if (sample_counter == 15) begin
                        if (rx_filtered == 1) begin
                            rx_data <= rx_shift_reg;
                            rx_ready_hold <= 2;
                        end else begin
                            rx_error <= 1;
                        end
                        state <= IDLE;
                    end
                end
            endcase
        end
    end
endmodule

SOURCE/uart_transmitter.v
module uart_transmitter(
    input wire clk,
    input wire rst,
    input wire baud_tick,
    input wire [7:0] tx_data,
    input wire tx_start,
    output reg tx_serial,
    output reg tx_busy,
    output reg tx_done
);

    localparam IDLE = 3'b000;
    localparam START = 3'b001;
    localparam DATA = 3'b010;
    localparam STOP = 3'b011;
    localparam DONE = 3'b100;

    reg [2:0] state;
    reg [2:0] bit_counter;
    reg [7:0] tx_shift_reg;

    always @(posedge clk or posedge rst) begin
        if (rst) begin
            state <= IDLE;
            tx_serial <= 1;
            tx_busy <= 0;
            tx_done <= 0;
            bit_counter <= 0;
            tx_shift_reg <= 0;
        end else begin
            case (state)
                IDLE: begin
                    tx_serial <= 1;
                    tx_busy <= 0;
                    tx_done <= 0;
                    if (tx_start) begin
                        tx_shift_reg <= tx_data;
                        tx_busy <= 1;
                        state <= START;
                    end
                end
                START: if (baud_tick) begin
                    tx_serial <= 0;
                    bit_counter <= 0;
                    state <= DATA;
                end
                DATA: if (baud_tick) begin
                    tx_serial <= tx_shift_reg[bit_counter];
                    bit_counter <= bit_counter + 1;
                    if (bit_counter == 7) state <= STOP;
                end
                STOP: if (baud_tick) begin
                    tx_serial <= 1;
                    state <= DONE;
                end
                DONE: if (baud_tick) begin
                    tx_done <= 1;
                    state <= IDLE;
                end
            endcase
        end
    end
endmodule

uart_baud_rate_generator.v
module uart_baud_generator #(
    parameter CLOCK_FREQ = 100000,   
    parameter BAUD_RATE = 10000
)(
    input wire clk,
    input wire rst,
    output reg baud_tick,
    output reg baud_tick_16x
);

    localparam BAUD_DIVISOR_16X = CLOCK_FREQ / (BAUD_RATE * 16);
    localparam COUNTER_WIDTH = $clog2(BAUD_DIVISOR_16X);

    reg [COUNTER_WIDTH-1:0] counter;
    reg [3:0] oversample_counter;

    always @(posedge clk or posedge rst) begin
        if (rst) begin
            counter <= 0;
            oversample_counter <= 0;
            baud_tick <= 0;
            baud_tick_16x <= 0;
        end else begin
            if (counter == BAUD_DIVISOR_16X - 1) begin
                counter <= 0;
                baud_tick_16x <= 1;
                oversample_counter <= oversample_counter + 1;

                if (oversample_counter == 15) begin
                    baud_tick <= 1;
                    oversample_counter <= 0;
                end else begin
                    baud_tick <= 0;
                end
            end else begin
                counter <= counter + 1;
                baud_tick <= 0;
                baud_tick_16x <= 0;
            end
        end
    end

endmodule

SOURCE/uart_top_module.v

module uart_top_level #(
    parameter CLOCK_FREQ = 1000000,
    parameter BAUD_RATE = 10000
)(
    input wire clk,
    input wire rst,

    input wire [7:0] tx_data,
    input wire tx_start,
    output wire tx_serial,
    output wire tx_busy,
    output wire tx_done,

    input wire rx_serial,
    output wire [7:0] rx_data,
    output wire rx_ready,
    output wire rx_error
);

    wire baud_tick;
    wire baud_tick_16x;

    uart_baud_generator #(
        .CLOCK_FREQ(CLOCK_FREQ),
        .BAUD_RATE(BAUD_RATE)
    ) baud_generator_inst (
        .clk(clk),
        .rst(rst),
        .baud_tick(baud_tick),
        .baud_tick_16x(baud_tick_16x)
    );

    uart_transmitter transmitter_inst (
        .clk(clk),
        .rst(rst),
        .baud_tick(baud_tick),
        .tx_data(tx_data),
        .tx_start(tx_start),
        .tx_serial(tx_serial),
        .tx_busy(tx_busy),
        .tx_done(tx_done)
    );

    uart_receiver receiver_inst (
        .clk(clk),
        .rst(rst),
        .baud_tick_16x(baud_tick_16x),
        .rx_serial(rx_serial),
        .rx_data(rx_data),
        .rx_ready(rx_ready),
        .rx_error(rx_error)
    );

endmodule

TESTBENCHES/top_tb_new.v
`timescale 1ns/1ps

module top_tb;

    reg clk;
    reg rst;

    reg [7:0] tx_data;
    reg tx_start;
    wire tx_serial;
    wire tx_busy;
    wire tx_done;

    wire [7:0] rx_data;
    wire rx_ready;
    wire rx_error;

    uart_top_level #(
        .CLOCK_FREQ(1000000),  
        .BAUD_RATE(10000)
    ) uut (
        .clk(clk),
        .rst(rst),
        .tx_data(tx_data),
        .tx_start(tx_start),
        .tx_serial(tx_serial),
        .tx_busy(tx_busy),
        .tx_done(tx_done),
        .rx_serial(tx_serial), 
        .rx_data(rx_data),
        .rx_ready(rx_ready),
        .rx_error(rx_error)
    );

    initial begin
        clk = 0;
        forever #5 clk = ~clk;
    end

    reg [7:0] test_data [0:4];
    integer i;

    initial begin
        $dumpfile("uart_top.vcd");
        $dumpvars(0, top_tb);

        rst = 1;
        tx_start = 0;
        tx_data = 8'h00;

        test_data[0] = 8'h08;
        test_data[1] = 8'h31;
        test_data[2] = 8'h69;
        test_data[3] = 8'h23;
        test_data[4] = 8'hBB;

        #1000;
        rst = 0;
        #1000;

        // Test sending multiple bytes
        for (i = 0; i < 5; i = i + 1) begin
            tx_data = test_data[i];
            $display("Sending data: 0x%02X at time %t", tx_data, $time);

            tx_start = 1;
            #20;
            tx_start = 0;

            wait (tx_done == 1);
            $display("Transmission completed at time %t", $time);

            receive_or_timeout(test_data[i]);

            #5000;
        end

        $display("Complete UART system test completed");
        $finish;
    end

    always @(posedge rx_error) begin
        $display("ERROR: Receiver error detected at time %t", $time);
    end

    always @(posedge clk) begin
        if (rx_ready) begin
            $display("RX_READY: Data 0x%02X received at time %t", rx_data, $time);
        end
    end

    task receive_or_timeout;
        input [7:0] expected_data;
        integer timeout_count;
        begin
            timeout_count = 0;
            while (rx_ready !== 1 && timeout_count < 20000) begin
                #1;
                timeout_count = timeout_count + 1;
            end

            if (rx_ready == 1) begin
                if (rx_data == expected_data) begin
                    $display("SUCCESS: Received 0x%02X matches sent data", rx_data);
                end else begin
                    $display("ERROR: Received 0x%02X does not match sent 0x%02X", rx_data, expected_data);
                end
            end 
        end
    endtask

endmodule

uart_top.vcd
$date
	Wed Aug 06 12:10:52 2025
$end
$version
	Icarus Verilog
$end
$timescale
	1ps
$end
$scope module top_tb $end
$var wire 8 ! rx_data [7:0] $end
$var wire 1 " rx_error $end
$var wire 1 # rx_ready $end
$var wire 1 $ tx_busy $end
$var wire 1 % tx_done $end
$var wire 1 & tx_serial $end
$var reg 1 ' clk $end
$var integer 32 ( i [31:0] $end
$var reg 1 ) rst $end
$var reg 8 * tx_data [7:0] $end
$var reg 1 + tx_start $end
$scope module uut $end
$var wire 1 , baud_tick $end
$var wire 1 - baud_tick_16x $end
$var wire 1 . clk $end
$var wire 1 / rst $end
$var wire 8 0 rx_data [7:0] $end
$var wire 1 " rx_error $end
$var wire 1 # rx_ready $end
$var wire 1 & rx_serial $end
$var wire 1 $ tx_busy $end
$var wire 8 1 tx_data [7:0] $end
$var wire 1 % tx_done $end
$var wire 1 & tx_serial $end
$var wire 1 2 tx_start $end
$scope module baud_generator_inst $end
$var wire 1 . clk $end
$var wire 1 / rst $end
$var reg 1 3 baud_tick $end
$var reg 1 4 baud_tick_16x $end
$var reg 4 5 counter [3:0] $end
$var reg 4 6 oversample_counter [3:0] $end
$upscope $end
$scope module transmitter_inst $end
$var wire 1 , baud_tick $end
$var wire 1 . clk $end
$var wire 1 / rst $end
$var wire 8 7 tx_data [7:0] $end
$var wire 1 2 tx_start $end
$var reg 3 8 bit_counter [2:0] $end
$var reg 3 9 state [2:0] $end
$var reg 1 : tx_busy $end
$var reg 1 ; tx_done $end
$var reg 1 < tx_serial $end
$var reg 8 = tx_shift_reg [7:0] $end
$upscope $end
$scope module receiver_inst $end
$var wire 1 - baud_tick_16x $end
$var wire 1 . clk $end
$var wire 1 / rst $end
$var wire 1 > rx_filtered $end
$var wire 1 & rx_serial $end
$var wire 1 ? start_bit_detected $end
$var reg 3 @ bit_counter [2:0] $end
$var reg 1 A prev_rx_filtered $end
$var reg 8 B rx_data [7:0] $end
$var reg 1 C rx_error $end
$var reg 1 D rx_ready $end
$var reg 2 E rx_ready_hold [1:0] $end
$var reg 8 F rx_shift_reg [7:0] $end
$var reg 3 G rx_sync [2:0] $end
$var reg 4 H sample_counter [3:0] $end
$var reg 3 I state [2:0] $end
$upscope $end
$upscope $end
$scope task receive_or_timeout $end
$var reg 8 J expected_data [7:0] $end
$var integer 32 K timeout_count [31:0] $end
$upscope $end
$upscope $end
$enddefinitions $end
#0
$dumpvars
bx K
bx J
b0 I
b0 H
b111 G
b0 F
b0 E
0D
0C
bx B
1A
b0 @
0?
1>
b0 =
1<
0;
0:
b0 9
b0 8
b0 7
b0 6
b0 5
04
03
02
b0 1
bx 0
1/
0.
0-
0,
0+
b0 *
1)
bx (
0'
1&
0%
0$
0#
0"
bx !
$end
#5000
1'
1.
#10000
0'
0.
#15000
1'
1.
#20000
0'
0.
#25000
1'
1.
#30000
0'
0.
#35000
1'
1.
#40000
0'
0.
#45000
1'
1.
#50000
0'
0.
#55000
1'
1.
#60000
0'
0.
#65000
1'
1.
#70000
0'
0.
#75000
1'
1.
#80000
0'
0.
#85000
1'
1.
#90000
0'
0.
#95000
1'
1.
#100000
0'
0.
#105000
1'
1.
#110000
0'
0.
#115000
1'
1.
#120000
0'
0.
#125000
1'
1.
#130000
0'
0.
#135000
1'
1.
#140000
0'
0.
#145000
1'
1.
#150000
0'
0.
#155000
1'
1.
#160000
0'
0.
#165000
1'
1.
#170000
0'
0.
#175000
1'
1.
#180000
0'
0.
#185000
1'
1.
#190000
0'
0.
#195000
1'
1.
#200000
0'
0.
#205000
1'
1.
#210000
0'
0.
#215000
1'
1.
#220000
0'
0.
#225000
1'
1.
#230000
0'
0.
#235000
1'
1.
#240000
0'
0.
#245000
1'
1.
#250000
0'
0.
#255000
1'
1.
#260000
0'
0.
#265000
1'
1.
#270000
0'
0.
#275000
1'
1.
#280000
0'
0.
#285000
1'
1.
#290000
0'
0.
#295000
1'
1.
#300000
0'
0.
#305000
1'
1.
#310000
0'
0.
#315000
1'
1.
#320000
0'
0.
#325000
1'
1.
#330000
0'
0.
#335000
1'
1.
#340000
0'
0.
#345000
1'
1.
#350000
0'
0.
#355000
1'
1.
#360000
0'
0.
#365000
1'
1.
#370000
0'
0.
#375000
1'
1.
#380000
0'
0.
#385000
1'
1.
#390000
0'
0.
#395000
1'
1.
#400000
0'
0.
#405000
1'
1.
#410000
0'
0.
#415000
1'
1.
#420000
0'
0.
#425000
1'
1.
#430000
0'
0.
#435000
1'
1.
#440000
0'
0.
#445000
1'
1.
#450000
0'
0.
#455000
1'
1.
#460000
0'
0.
#465000
1'
1.
#470000
0'
0.
#475000
1'
1.
#480000
0'
0.
#485000
1'
1.
#490000
0'
0.
#495000
1'
1.
#500000
0'
0.
#505000
1'
1.
#510000
0'
0.
#515000
1'
1.
#520000
0'
0.
#525000
1'
1.
#530000
0'
0.
#535000
1'
1.
#540000
0'
0.
#545000
1'
1.
#550000
0'
0.
#555000
1'
1.
#560000
0'
0.
#565000
1'
1.
#570000
0'
0.
#575000
1'
1.
#580000
0'
0.
#585000
1'
1.
#590000
0'
0.
#595000
1'
1.
#600000
0'
0.
#605000
1'
1.
#610000
0'
0.
#615000
1'
1.
#620000
0'
0.
#625000
1'
1.
#630000
0'
0.
#635000
1'
1.
#640000
0'
0.
#645000
1'
1.
#650000
0'
0.
#655000
1'
1.
#660000
0'
0.
#665000
1'
1.
#670000
0'
0.
#675000
1'
1.
#680000
0'
0.
#685000
1'
1.
#690000
0'
0.
#695000
1'
1.
#700000
0'
0.
#705000
1'
1.
#710000
0'
0.
#715000
1'
1.
#720000
0'
0.
#725000
1'
1.
#730000
0'
0.
#735000
1'
1.
#740000
0'
0.
#745000
1'
1.
#750000
0'
0.
#755000
1'
1.
#760000
0'
0.
#765000
1'
1.
#770000
0'
0.
#775000
1'
1.
#780000
0'
0.
#785000
1'
1.
#790000
0'
0.
#795000
1'
1.
#800000
0'
0.
#805000
1'
1.
#810000
0'
0.
#815000
1'
1.
#820000
0'
0.
#825000
1'
1.
#830000
0'
0.
#835000
1'
1.
#840000
0'
0.
#845000
1'
1.
#850000
0'
0.
#855000
1'
1.
#860000
0'
0.
#865000
1'
1.
#870000
0'
0.
#875000
1'
1.
#880000
0'
0.
#885000
1'
1.
#890000
0'
0.
#895000
1'
1.
#900000
0'
0.
#905000
1'
1.
#910000
0'
0.
#915000
1'
1.
#920000
0'
0.
#925000
1'
1.
#930000
0'
0.
#935000
1'
1.
#940000
0'
0.
#945000
1'
1.
#950000
0'
0.
#955000
1'
1.
#960000
0'
0.
#965000
1'
1.
#970000
0'
0.
#975000
1'
1.
#980000
0'
0.
#985000
1'
1.
#990000
0'
0.
#995000
1'
1.
#1000000
0'
0.
0)
0/
#1005000
b1 5
1'
1.
#1010000
0'
0.
#1015000
b10 5
1'
1.
#1020000
0'
0.
#1025000
b11 5
1'
1.
#1030000
0'
0.
#1035000
b100 5
1'
1.
#1040000
0'
0.
#1045000
b101 5
1'
1.
#1050000
0'
0.
#1055000
b110 5
1'
1.
#1060000
0'
0.
#1065000
b111 5
1'
1.
#1070000
0'
0.
#1075000
b1000 5
1'
1.
#1080000
0'
0.
#1085000
b1001 5
1'
1.
#1090000
0'
0.
#1095000
b1 6
14
1-
b0 5
1'
1.
#1100000
0'
0.
#1105000
04
0-
b1 5
1'
1.
#1110000
0'
0.
#1115000
b10 5
1'
1.
#1120000
0'
0.
#1125000
b11 5
1'
1.
#1130000
0'
0.
#1135000
b100 5
1'
1.
#1140000
0'
0.
#1145000
b101 5
1'
1.
#1150000
0'
0.
#1155000
b110 5
1'
1.
#1160000
0'
0.
#1165000
b111 5
1'
1.
#1170000
0'
0.
#1175000
b1000 5
1'
1.
#1180000
0'
0.
#1185000
b1001 5
1'
1.
#1190000
0'
0.
#1195000
b10 6
14
1-
b0 5
1'
1.
#1200000
0'
0.
#1205000
04
0-
b1 5
1'
1.
#1210000
0'
0.
#1215000
b10 5
1'
1.
#1220000
0'
0.
#1225000
b11 5
1'
1.
#1230000
0'
0.
#1235000
b100 5
1'
1.
#1240000
0'
0.
#1245000
b101 5
1'
1.
#1250000
0'
0.
#1255000
b110 5
1'
1.
#1260000
0'
0.
#1265000
b111 5
1'
1.
#1270000
0'
0.
#1275000
b1000 5
1'
1.
#1280000
0'
0.
#1285000
b1001 5
1'
1.
#1290000
0'
0.
#1295000
b11 6
14
1-
b0 5
1'
1.
#1300000
0'
0.
#1305000
04
0-
b1 5
1'
1.
#1310000
0'
0.
#1315000
b10 5
1'
1.
#1320000
0'
0.
#1325000
b11 5
1'
1.
#1330000
0'
0.
#1335000
b100 5
1'
1.
#1340000
0'
0.
#1345000
b101 5
1'
1.
#1350000
0'
0.
#1355000
b110 5
1'
1.
#1360000
0'
0.
#1365000
b111 5
1'
1.
#1370000
0'
0.
#1375000
b1000 5
1'
1.
#1380000
0'
0.
#1385000
b1001 5
1'
1.
#1390000
0'
0.
#1395000
b100 6
14
1-
b0 5
1'
1.
#1400000
0'
0.
#1405000
04
0-
b1 5
1'
1.
#1410000
0'
0.
#1415000
b10 5
1'
1.
#1420000
0'
0.
#1425000
b11 5
1'
1.
#1430000
0'
0.
#1435000
b100 5
1'
1.
#1440000
0'
0.
#1445000
b101 5
1'
1.
#1450000
0'
0.
#1455000
b110 5
1'
1.
#1460000
0'
0.
#1465000
b111 5
1'
1.
#1470000
0'
0.
#1475000
b1000 5
1'
1.
#1480000
0'
0.
#1485000
b1001 5
1'
1.
#1490000
0'
0.
#1495000
b101 6
14
1-
b0 5
1'
1.
#1500000
0'
0.
#1505000
04
0-
b1 5
1'
1.
#1510000
0'
0.
#1515000
b10 5
1'
1.
#1520000
0'
0.
#1525000
b11 5
1'
1.
#1530000
0'
0.
#1535000
b100 5
1'
1.
#1540000
0'
0.
#1545000
b101 5
1'
1.
#1550000
0'
0.
#1555000
b110 5
1'
1.
#1560000
0'
0.
#1565000
b111 5
1'
1.
#1570000
0'
0.
#1575000
b1000 5
1'
1.
#1580000
0'
0.
#1585000
b1001 5
1'
1.
#1590000
0'
0.
#1595000
b110 6
14
1-
b0 5
1'
1.
#1600000
0'
0.
#1605000
04
0-
b1 5
1'
1.
#1610000
0'
0.
#1615000
b10 5
1'
1.
#1620000
0'
0.
#1625000
b11 5
1'
1.
#1630000
0'
0.
#1635000
b100 5
1'
1.
#1640000
0'
0.
#1645000
b101 5
1'
1.
#1650000
0'
0.
#1655000
b110 5
1'
1.
#1660000
0'
0.
#1665000
b111 5
1'
1.
#1670000
0'
0.
#1675000
b1000 5
1'
1.
#1680000
0'
0.
#1685000
b1001 5
1'
1.
#1690000
0'
0.
#1695000
b111 6
14
1-
b0 5
1'
1.
#1700000
0'
0.
#1705000
04
0-
b1 5
1'
1.
#1710000
0'
0.
#1715000
b10 5
1'
1.
#1720000
0'
0.
#1725000
b11 5
1'
1.
#1730000
0'
0.
#1735000
b100 5
1'
1.
#1740000
0'
0.
#1745000
b101 5
1'
1.
#1750000
0'
0.
#1755000
b110 5
1'
1.
#1760000
0'
0.
#1765000
b111 5
1'
1.
#1770000
0'
0.
#1775000
b1000 5
1'
1.
#1780000
0'
0.
#1785000
b1001 5
1'
1.
#1790000
0'
0.
#1795000
b1000 6
14
1-
b0 5
1'
1.
#1800000
0'
0.
#1805000
04
0-
b1 5
1'
1.
#1810000
0'
0.
#1815000
b10 5
1'
1.
#1820000
0'
0.
#1825000
b11 5
1'
1.
#1830000
0'
0.
#1835000
b100 5
1'
1.
#1840000
0'
0.
#1845000
b101 5
1'
1.
#1850000
0'
0.
#1855000
b110 5
1'
1.
#1860000
0'
0.
#1865000
b111 5
1'
1.
#1870000
0'
0.
#1875000
b1000 5
1'
1.
#1880000
0'
0.
#1885000
b1001 5
1'
1.
#1890000
0'
0.
#1895000
b1001 6
14
1-
b0 5
1'
1.
#1900000
0'
0.
#1905000
04
0-
b1 5
1'
1.
#1910000
0'
0.
#1915000
b10 5
1'
1.
#1920000
0'
0.
#1925000
b11 5
1'
1.
#1930000
0'
0.
#1935000
b100 5
1'
1.
#1940000
0'
0.
#1945000
b101 5
1'
1.
#1950000
0'
0.
#1955000
b110 5
1'
1.
#1960000
0'
0.
#1965000
b111 5
1'
1.
#1970000
0'
0.
#1975000
b1000 5
1'
1.
#1980000
0'
0.
#1985000
b1001 5
1'
1.
#1990000
0'
0.
#1995000
b1010 6
14
1-
b0 5
1'
1.
#2000000
0'
0.
1+
12
b1000 *
b1000 1
b1000 7
b0 (
#2005000
b1 9
1:
1$
b1000 =
04
0-
b1 5
1'
1.
#2010000
0'
0.
#2015000
b10 5
1'
1.
#2020000
0'
0.
0+
02
#2025000
b11 5
1'
1.
#2030000
0'
0.
#2035000
b100 5
1'
1.
#2040000
0'
0.
#2045000
b101 5
1'
1.
#2050000
0'
0.
#2055000
b110 5
1'
1.
#2060000
0'
0.
#2065000
b111 5
1'
1.
#2070000
0'
0.
#2075000
b1000 5
1'
1.
#2080000
0'
0.
#2085000
b1001 5
1'
1.
#2090000
0'
0.
#2095000
b1011 6
14
1-
b0 5
1'
1.
#2100000
0'
0.
#2105000
04
0-
b1 5
1'
1.
#2110000
0'
0.
#2115000
b10 5
1'
1.
#2120000
0'
0.
#2125000
b11 5
1'
1.
#2130000
0'
0.
#2135000
b100 5
1'
1.
#2140000
0'
0.
#2145000
b101 5
1'
1.
#2150000
0'
0.
#2155000
b110 5
1'
1.
#2160000
0'
0.
#2165000
b111 5
1'
1.
#2170000
0'
0.
#2175000
b1000 5
1'
1.
#2180000
0'
0.
#2185000
b1001 5
1'
1.
#2190000
0'
0.
#2195000
b1100 6
14
1-
b0 5
1'
1.
#2200000
0'
0.
#2205000
04
0-
b1 5
1'
1.
#2210000
0'
0.
#2215000
b10 5
1'
1.
#2220000
0'
0.
#2225000
b11 5
1'
1.
#2230000
0'
0.
#2235000
b100 5
1'
1.
#2240000
0'
0.
#2245000
b101 5
1'
1.
#2250000
0'
0.
#2255000
b110 5
1'
1.
#2260000
0'
0.
#2265000
b111 5
1'
1.
#2270000
0'
0.
#2275000
b1000 5
1'
1.
#2280000
0'
0.
#2285000
b1001 5
1'
1.
#2290000
0'
0.
#2295000
b1101 6
14
1-
b0 5
1'
1.
#2300000
0'
0.
#2305000
04
0-
b1 5
1'
1.
#2310000
0'
0.
#2315000
b10 5
1'
1.
#2320000
0'
0.
#2325000
b11 5
1'
1.
#2330000
0'
0.
#2335000
b100 5
1'
1.
#2340000
0'
0.
#2345000
b101 5
1'
1.
#2350000
0'
0.
#2355000
b110 5
1'
1.
#2360000
0'
0.
#2365000
b111 5
1'
1.
#2370000
0'
0.
#2375000
b1000 5
1'
1.
#2380000
0'
0.
#2385000
b1001 5
1'
1.
#2390000
0'
0.
#2395000
b1110 6
14
1-
b0 5
1'
1.
#2400000
0'
0.
#2405000
04
0-
b1 5
1'
1.
#2410000
0'
0.
#2415000
b10 5
1'
1.
#2420000
0'
0.
#2425000
b11 5
1'
1.
#2430000
0'
0.
#2435000
b100 5
1'
1.
#2440000
0'
0.
#2445000
b101 5
1'
1.
#2450000
0'
0.
#2455000
b110 5
1'
1.
#2460000
0'
0.
#2465000
b111 5
1'
1.
#2470000
0'
0.
#2475000
b1000 5
1'
1.
#2480000
0'
0.
#2485000
b1001 5
1'
1.
#2490000
0'
0.
#2495000
b1111 6
14
1-
b0 5
1'
1.
#2500000
0'
0.
#2505000
04
0-
b1 5
1'
1.
#2510000
0'
0.
#2515000
b10 5
1'
1.
#2520000
0'
0.
#2525000
b11 5
1'
1.
#2530000
0'
0.
#2535000
b100 5
1'
1.
#2540000
0'
0.
#2545000
b101 5
1'
1.
#2550000
0'
0.
#2555000
b110 5
1'
1.
#2560000
0'
0.
#2565000
b111 5
1'
1.
#2570000
0'
0.
#2575000
b1000 5
1'
1.
#2580000
0'
0.
#2585000
b1001 5
1'
1.
#2590000
0'
0.
#2595000
13
1,
b0 6
14
1-
b0 5
1'
1.
#2600000
0'
0.
#2605000
b10 9
0<
0&
04
0-
03
0,
b1 5
1'
1.
#2610000
0'
0.
#2615000
b10 5
b110 G
1'
1.
#2620000
0'
0.
#2625000
b100 G
b11 5
1'
1.
#2630000
0'
0.
#2635000
1?
0>
b100 5
b0 G
1'
1.
#2640000
0'
0.
#2645000
0?
b1 I
0A
b101 5
1'
1.
#2650000
0'
0.
#2655000
b110 5
1'
1.
#2660000
0'
0.
#2665000
b111 5
1'
1.
#2670000
0'
0.
#2675000
b1000 5
1'
1.
#2680000
0'
0.
#2685000
b1001 5
1'
1.
#2690000
0'
0.
#2695000
b1 6
14
1-
b0 5
1'
1.
#2700000
0'
0.
#2705000
b1 H
04
0-
b1 5
1'
1.
#2710000
0'
0.
#2715000
b10 5
1'
1.
#2720000
0'
0.
#2725000
b11 5
1'
1.
#2730000
0'
0.
#2735000
b100 5
1'
1.
#2740000
0'
0.
#2745000
b101 5
1'
1.
#2750000
0'
0.
#2755000
b110 5
1'
1.
#2760000
0'
0.
#2765000
b111 5
1'
1.
#2770000
0'
0.
#2775000
b1000 5
1'
1.
#2780000
0'
0.
#2785000
b1001 5
1'
1.
#2790000
0'
0.
#2795000
b10 6
14
1-
b0 5
1'
1.
#2800000
0'
0.
#2805000
b10 H
04
0-
b1 5
1'
1.
#2810000
0'
0.
#2815000
b10 5
1'
1.
#2820000
0'
0.
#2825000
b11 5
1'
1.
#2830000
0'
0.
#2835000
b100 5
1'
1.
#2840000
0'
0.
#2845000
b101 5
1'
1.
#2850000
0'
0.
#2855000
b110 5
1'
1.
#2860000
0'
0.
#2865000
b111 5
1'
1.
#2870000
0'
0.
#2875000
b1000 5
1'
1.
#2880000
0'
0.
#2885000
b1001 5
1'
1.
#2890000
0'
0.
#2895000
b11 6
14
1-
b0 5
1'
1.
#2900000
0'
0.
#2905000
b11 H
04
0-
b1 5
1'
1.
#2910000
0'
0.
#2915000
b10 5
1'
1.
#2920000
0'
0.
#2925000
b11 5
1'
1.
#2930000
0'
0.
#2935000
b100 5
1'
1.
#2940000
0'
0.
#2945000
b101 5
1'
1.
#2950000
0'
0.
#2955000
b110 5
1'
1.
#2960000
0'
0.
#2965000
b111 5
1'
1.
#2970000
0'
0.
#2975000
b1000 5
1'
1.
#2980000
0'
0.
#2985000
b1001 5
1'
1.
#2990000
0'
0.
#2995000
b100 6
14
1-
b0 5
1'
1.
#3000000
0'
0.
#3005000
b100 H
04
0-
b1 5
1'
1.
#3010000
0'
0.
#3015000
b10 5
1'
1.
#3020000
0'
0.
#3025000
b11 5
1'
1.
#3030000
0'
0.
#3035000
b100 5
1'
1.
#3040000
0'
0.
#3045000
b101 5
1'
1.
#3050000
0'
0.
#3055000
b110 5
1'
1.
#3060000
0'
0.
#3065000
b111 5
1'
1.
#3070000
0'
0.
#3075000
b1000 5
1'
1.
#3080000
0'
0.
#3085000
b1001 5
1'
1.
#3090000
0'
0.
#3095000
b101 6
14
1-
b0 5
1'
1.
#3100000
0'
0.
#3105000
b101 H
04
0-
b1 5
1'
1.
#3110000
0'
0.
#3115000
b10 5
1'
1.
#3120000
0'
0.
#3125000
b11 5
1'
1.
#3130000
0'
0.
#3135000
b100 5
1'
1.
#3140000
0'
0.
#3145000
b101 5
1'
1.
#3150000
0'
0.
#3155000
b110 5
1'
1.
#3160000
0'
0.
#3165000
b111 5
1'
1.
#3170000
0'
0.
#3175000
b1000 5
1'
1.
#3180000
0'
0.
#3185000
b1001 5
1'
1.
#3190000
0'
0.
#3195000
b110 6
14
1-
b0 5
1'
1.
#3200000
0'
0.
#3205000
b110 H
04
0-
b1 5
1'
1.
#3210000
0'
0.
#3215000
b10 5
1'
1.
#3220000
0'
0.
#3225000
b11 5
1'
1.
#3230000
0'
0.
#3235000
b100 5
1'
1.
#3240000
0'
0.
#3245000
b101 5
1'
1.
#3250000
0'
0.
#3255000
b110 5
1'
1.
#3260000
0'
0.
#3265000
b111 5
1'
1.
#3270000
0'
0.
#3275000
b1000 5
1'
1.
#3280000
0'
0.
#3285000
b1001 5
1'
1.
#3290000
0'
0.
#3295000
b111 6
14
1-
b0 5
1'
1.
#3300000
0'
0.
#3305000
b111 H
04
0-
b1 5
1'
1.
#3310000
0'
0.
#3315000
b10 5
1'
1.
#3320000
0'
0.
#3325000
b11 5
1'
1.
#3330000
0'
0.
#3335000
b100 5
1'
1.
#3340000
0'
0.
#3345000
b101 5
1'
1.
#3350000
0'
0.
#3355000
b110 5
1'
1.
#3360000
0'
0.
#3365000
b111 5
1'
1.
#3370000
0'
0.
#3375000
b1000 5
1'
1.
#3380000
0'
0.
#3385000
b1001 5
1'
1.
#3390000
0'
0.
#3395000
b1000 6
14
1-
b0 5
1'
1.
#3400000
0'
0.
#3405000
b10 I
b0 H
04
0-
b1 5
1'
1.
#3410000
0'
0.
#3415000
b10 5
1'
1.
#3420000
0'
0.
#3425000
b11 5
1'
1.
#3430000
0'
0.
#3435000
b100 5
1'
1.
#3440000
0'
0.
#3445000
b101 5
1'
1.
#3450000
0'
0.
#3455000
b110 5
1'
1.
#3460000
0'
0.
#3465000
b111 5
1'
1.
#3470000
0'
0.
#3475000
b1000 5
1'
1.
#3480000
0'
0.
#3485000
b1001 5
1'
1.
#3490000
0'
0.
#3495000
b1001 6
14
1-
b0 5
1'
1.
#3500000
0'
0.
#3505000
b1 H
04
0-
b1 5
1'
1.
#3510000
0'
0.
#3515000
b10 5
1'
1.
#3520000
0'
0.
#3525000
b11 5
1'
1.
#3530000
0'
0.
#3535000
b100 5
1'
1.
#3540000
0'
0.
#3545000
b101 5
1'
1.
#3550000
0'
0.
#3555000
b110 5
1'
1.
#3560000
0'
0.
#3565000
b111 5
1'
1.
#3570000
0'
0.
#3575000
b1000 5
1'
1.
#3580000
0'
0.
#3585000
b1001 5
1'
1.
#3590000
0'
0.
